struct_diff/__init__.py
struct_diff/__main__.py
struct_diff/comparator.py
struct_diff/util.py
struct_diff/formatters/__init__.py
struct_diff/formatters/base.py
struct_diff/formatters/json.py
struct_diff/formatters/yaml.py
struct_diff-0.9.0.post7.dist-info/LICENSE
struct_diff-0.9.0.post7.dist-info/METADATA
struct_diff-0.9.0.post7.dist-info/WHEEL
struct_diff-0.9.0.post7.dist-info/top_level.txt
struct_diff-0.9.0.post7.dist-info/RECORD
