Metadata-Version: 2.1
Name: struct-diff
Version: 0.9.0.post7
Summary: Structural comparison of two objects.
Home-page: https://github.com/k3a/struct_diff
Author: K3A
License: MIT
License-File: LICENSE
